Compiled from "MappingConfiguration.java"
public class net.fabricmc.loom.configuration.providers.mappings.MappingConfiguration {
  public final java.lang.String mappingsIdentifier;

  public final java.nio.file.Path tinyMappings;

  public final java.nio.file.Path tinyMappingsJar;

  public static net.fabricmc.loom.configuration.providers.mappings.MappingConfiguration create(org.gradle.api.Project, net.fabricmc.loom.util.service.ServiceFactory, net.fabricmc.loom.configuration.DependencyInfo, net.fabricmc.loom.configuration.providers.minecraft.MinecraftProvider);
    Code:
       0: aload_2
       1: invokevirtual #43                 // Method net/fabricmc/loom/configuration/DependencyInfo.getResolvedVersion:()Ljava/lang/String;
       4: astore        4
       6: aload_2
       7: invokevirtual #49                 // Method net/fabricmc/loom/configuration/DependencyInfo.resolveFile:()Ljava/util/Optional;
      10: aload_2
      11: invokedynamic #53,  0             // InvokeDynamic #0:get:(Lnet/fabricmc/loom/configuration/DependencyInfo;)Ljava/util/function/Supplier;
      16: invokevirtual #57                 // Method java/util/Optional.orElseThrow:(Ljava/util/function/Supplier;)Ljava/lang/Object;
      19: checkcast     #63                 // class java/io/File
      22: invokevirtual #65                 // Method java/io/File.toPath:()Ljava/nio/file/Path;
      25: astore        5
      27: aload_2
      28: invokevirtual #69                 // Method net/fabricmc/loom/configuration/DependencyInfo.getDependency:()Lorg/gradle/api/artifacts/Dependency;
      31: invokeinterface #73,  1           // InterfaceMethod org/gradle/api/artifacts/Dependency.getGroup:()Ljava/lang/String;
      36: aload_2
      37: invokevirtual #69                 // Method net/fabricmc/loom/configuration/DependencyInfo.getDependency:()Lorg/gradle/api/artifacts/Dependency;
      40: invokeinterface #78,  1           // InterfaceMethod org/gradle/api/artifacts/Dependency.getName:()Ljava/lang/String;
      45: invokedynamic #81,  0             // InvokeDynamic #1:makeConcatWithConstants:(Ljava/lang/String;Ljava/lang/String;)Ljava/lang/String;
      50: ldc           #85                 // String -unmerged
      52: invokestatic  #87                 // Method org/apache/tools/ant/util/StringUtils.removeSuffix:(Ljava/lang/String;Ljava/lang/String;)Ljava/lang/String;
      55: astore        6
      57: aload         5
      59: invokestatic  #92                 // Method net/fabricmc/loom/configuration/providers/mappings/tiny/TinyJarInfo.get:(Ljava/nio/file/Path;)Lnet/fabricmc/loom/configuration/providers/mappings/tiny/TinyJarInfo;
      62: astore        7
      64: aload         7
      66: invokevirtual #97                 // Method net/fabricmc/loom/configuration/providers/mappings/tiny/TinyJarInfo.minecraftVersionId:()Ljava/util/Optional;
      69: aload_3
      70: aload_2
      71: invokedynamic #100,  0            // InvokeDynamic #2:accept:(Lnet/fabricmc/loom/configuration/providers/minecraft/MinecraftProvider;Lnet/fabricmc/loom/configuration/DependencyInfo;)Ljava/util/function/Consumer;
      76: invokevirtual #104                // Method java/util/Optional.ifPresent:(Ljava/util/function/Consumer;)V
      79: aload         6
      81: aload         4
      83: aload_2
      84: aload         7
      86: invokevirtual #108                // Method net/fabricmc/loom/configuration/providers/mappings/tiny/TinyJarInfo.v2:()Z
      89: invokestatic  #112                // Method getMappingsClassifier:(Lnet/fabricmc/loom/configuration/DependencyInfo;Z)Ljava/lang/String;
      92: aload_3
      93: invokevirtual #116                // Method net/fabricmc/loom/configuration/providers/minecraft/MinecraftProvider.minecraftVersion:()Ljava/lang/String;
      96: invokestatic  #121                // Method createMappingsIdentifier:(Ljava/lang/String;Ljava/lang/String;Ljava/lang/String;Ljava/lang/String;)Ljava/lang/String;
      99: astore        8
     101: aload_3
     102: aload         8
     104: invokevirtual #125                // Method net/fabricmc/loom/configuration/providers/minecraft/MinecraftProvider.dir:(Ljava/lang/String;)Ljava/io/File;
     107: invokevirtual #65                 // Method java/io/File.toPath:()Ljava/nio/file/Path;
     110: astore        9
     112: new           #8                  // class net/fabricmc/loom/configuration/providers/mappings/MappingConfiguration
     115: dup
     116: aload         8
     118: aload         9
     120: invokespecial #129                // Method "<init>":(Ljava/lang/String;Ljava/nio/file/Path;)V
     123: astore        10
     125: aload         10
     127: aload_0
     128: aload_1
     129: aload_3
     130: aload         5
     132: invokevirtual #132                // Method setup:(Lorg/gradle/api/Project;Lnet/fabricmc/loom/util/service/ServiceFactory;Lnet/fabricmc/loom/configuration/providers/minecraft/MinecraftProvider;Ljava/nio/file/Path;)V
     135: goto          164
     138: astore        11
     140: aload         9
     142: invokestatic  #138                // Method cleanWorkingDirectory:(Ljava/nio/file/Path;)V
     145: new           #142                // class java/io/UncheckedIOException
     148: dup
     149: aload_2
     150: invokevirtual #144                // Method net/fabricmc/loom/configuration/DependencyInfo.getDepString:()Ljava/lang/String;
     153: invokedynamic #147,  0            // InvokeDynamic #3:makeConcatWithConstants:(Ljava/lang/String;)Ljava/lang/String;
     158: aload         11
     160: invokespecial #150                // Method java/io/UncheckedIOException."<init>":(Ljava/lang/String;Ljava/io/IOException;)V
     163: athrow
     164: aload         10
     166: areturn
    Exception table:
       from    to  target type
         125   135   138   Class java/io/IOException

  public org.gradle.api.provider.Provider<net.fabricmc.loom.configuration.providers.mappings.TinyMappingsService$Options> getMappingsServiceOptions(org.gradle.api.Project);
    Code:
       0: aload_1
       1: aload_0
       2: getfield      #30                 // Field tinyMappings:Ljava/nio/file/Path;
       5: invokestatic  #153                // Method java/util/Objects.requireNonNull:(Ljava/lang/Object;)Ljava/lang/Object;
       8: checkcast     #20                 // class java/nio/file/Path
      11: invokestatic  #159                // Method net/fabricmc/loom/configuration/providers/mappings/TinyMappingsService.createOptions:(Lorg/gradle/api/Project;Ljava/nio/file/Path;)Lorg/gradle/api/provider/Provider;
      14: areturn

  public net.fabricmc.loom.configuration.providers.mappings.TinyMappingsService getMappingsService(org.gradle.api.Project, net.fabricmc.loom.util.service.ServiceFactory);
    Code:
       0: aload_2
       1: aload_0
       2: aload_1
       3: invokevirtual #165                // Method getMappingsServiceOptions:(Lorg/gradle/api/Project;)Lorg/gradle/api/provider/Provider;
       6: invokeinterface #169,  2          // InterfaceMethod net/fabricmc/loom/util/service/ServiceFactory.get:(Lorg/gradle/api/provider/Provider;)Lnet/fabricmc/loom/util/service/Service;
      11: checkcast     #160                // class net/fabricmc/loom/configuration/providers/mappings/TinyMappingsService
      14: areturn

  public void applyToProject(org.gradle.api.Project, net.fabricmc.loom.configuration.DependencyInfo);
    Code:
       0: aload_0
       1: getfield      #227                // Field unpickMetadata:Lnet/fabricmc/loom/configuration/providers/mappings/unpick/UnpickMetadata;
       4: ifnull        168
       7: aload_0
       8: getfield      #227                // Field unpickMetadata:Lnet/fabricmc/loom/configuration/providers/mappings/unpick/UnpickMetadata;
      11: invokeinterface #231,  1          // InterfaceMethod net/fabricmc/loom/configuration/providers/mappings/unpick/UnpickMetadata.hasConstants:()Z
      16: ifeq          168
      19: aload_0
      20: getfield      #227                // Field unpickMetadata:Lnet/fabricmc/loom/configuration/providers/mappings/unpick/UnpickMetadata;
      23: dup
      24: invokestatic  #153                // Method java/util/Objects.requireNonNull:(Ljava/lang/Object;)Ljava/lang/Object;
      27: pop
      28: astore        4
      30: iconst_0
      31: istore        5
      33: aload         4
      35: iload         5
      37: invokedynamic #236,  0            // InvokeDynamic #4:typeSwitch:(Ljava/lang/Object;I)I
      42: lookupswitch  { // 2
                     0: 78
                     1: 133
               default: 68
          }
      68: new           #240                // class java/lang/MatchException
      71: dup
      72: aconst_null
      73: aconst_null
      74: invokespecial #242                // Method java/lang/MatchException."<init>":(Ljava/lang/String;Ljava/lang/Throwable;)V
      77: athrow
      78: aload         4
      80: checkcast     #245                // class net/fabricmc/loom/configuration/providers/mappings/unpick/UnpickMetadata$V1
      83: astore        6
      85: ldc           #247                // String %s:%s:%s:constants
      87: iconst_3
      88: anewarray     #2                  // class java/lang/Object
      91: dup
      92: iconst_0
      93: aload_2
      94: invokevirtual #69                 // Method net/fabricmc/loom/configuration/DependencyInfo.getDependency:()Lorg/gradle/api/artifacts/Dependency;
      97: invokeinterface #73,  1           // InterfaceMethod org/gradle/api/artifacts/Dependency.getGroup:()Ljava/lang/String;
     102: aastore
     103: dup
     104: iconst_1
     105: aload_2
     106: invokevirtual #69                 // Method net/fabricmc/loom/configuration/DependencyInfo.getDependency:()Lorg/gradle/api/artifacts/Dependency;
     109: invokeinterface #78,  1           // InterfaceMethod org/gradle/api/artifacts/Dependency.getName:()Ljava/lang/String;
     114: aastore
     115: dup
     116: iconst_2
     117: aload_2
     118: invokevirtual #69                 // Method net/fabricmc/loom/configuration/DependencyInfo.getDependency:()Lorg/gradle/api/artifacts/Dependency;
     121: invokeinterface #249,  1          // InterfaceMethod org/gradle/api/artifacts/Dependency.getVersion:()Ljava/lang/String;
     126: aastore
     127: invokestatic  #252                // Method java/lang/String.format:(Ljava/lang/String;[Ljava/lang/Object;)Ljava/lang/String;
     130: goto          151
     133: aload         4
     135: checkcast     #258                // class net/fabricmc/loom/configuration/providers/mappings/unpick/UnpickMetadata$V2
     138: astore        7
     140: aload         7
     142: invokevirtual #260                // Method net/fabricmc/loom/configuration/providers/mappings/unpick/UnpickMetadata$V2.constants:()Ljava/lang/String;
     145: invokestatic  #153                // Method java/util/Objects.requireNonNull:(Ljava/lang/Object;)Ljava/lang/Object;
     148: checkcast     #253                // class java/lang/String
     151: astore_3
     152: aload_1
     153: invokeinterface #263,  1          // InterfaceMethod org/gradle/api/Project.getDependencies:()Lorg/gradle/api/artifacts/dsl/DependencyHandler;
     158: ldc_w         #271                // String mappingsConstants
     161: aload_3
     162: invokeinterface #273,  3          // InterfaceMethod org/gradle/api/artifacts/dsl/DependencyHandler.add:(Ljava/lang/String;Ljava/lang/Object;)Lorg/gradle/api/artifacts/Dependency;
     167: pop
     168: aload_1
     169: invokeinterface #263,  1          // InterfaceMethod org/gradle/api/Project.getDependencies:()Lorg/gradle/api/artifacts/dsl/DependencyHandler;
     174: ldc_w         #278                // String mappingsFinal
     177: aload_1
     178: iconst_1
     179: anewarray     #2                  // class java/lang/Object
     182: dup
     183: iconst_0
     184: aload_0
     185: getfield      #35                 // Field tinyMappingsJar:Ljava/nio/file/Path;
     188: invokeinterface #280,  1          // InterfaceMethod java/nio/file/Path.toFile:()Ljava/io/File;
     193: aastore
     194: invokeinterface #284,  2          // InterfaceMethod org/gradle/api/Project.files:([Ljava/lang/Object;)Lorg/gradle/api/file/ConfigurableFileCollection;
     199: invokeinterface #273,  3          // InterfaceMethod org/gradle/api/artifacts/dsl/DependencyHandler.add:(Ljava/lang/String;Ljava/lang/Object;)Lorg/gradle/api/artifacts/Dependency;
     204: pop
     205: return

  public static void extractMappings(java.nio.file.Path, java.nio.file.Path) throws java.io.IOException;
    Code:
       0: aload_0
       1: invokestatic  #317                // Method net/fabricmc/loom/util/FileSystemUtil.getJarFileSystem:(Ljava/nio/file/Path;)Lnet/fabricmc/loom/util/FileSystemUtil$Delegate;
       4: astore_2
       5: aload_2
       6: invokevirtual #323                // Method net/fabricmc/loom/util/FileSystemUtil$Delegate.fs:()Ljava/nio/file/FileSystem;
       9: aload_1
      10: invokestatic  #329                // Method extractMappings:(Ljava/nio/file/FileSystem;Ljava/nio/file/Path;)V
      13: aload_2
      14: ifnull        46
      17: aload_2
      18: invokevirtual #333                // Method net/fabricmc/loom/util/FileSystemUtil$Delegate.close:()V
      21: goto          46
      24: astore_3
      25: aload_2
      26: ifnull        44
      29: aload_2
      30: invokevirtual #333                // Method net/fabricmc/loom/util/FileSystemUtil$Delegate.close:()V
      33: goto          44
      36: astore        4
      38: aload_3
      39: aload         4
      41: invokevirtual #207                // Method java/lang/Throwable.addSuppressed:(Ljava/lang/Throwable;)V
      44: aload_3
      45: athrow
      46: return
    Exception table:
       from    to  target type
           5    13    24   Class java/lang/Throwable
          29    33    36   Class java/lang/Throwable

  public static void extractMappings(java.nio.file.FileSystem, java.nio.file.Path) throws java.io.IOException;
    Code:
       0: aload_0
       1: ldc           #215                // String mappings/mappings.tiny
       3: iconst_0
       4: anewarray     #253                // class java/lang/String
       7: invokevirtual #392                // Method java/nio/file/FileSystem.getPath:(Ljava/lang/String;[Ljava/lang/String;)Ljava/nio/file/Path;
      10: aload_1
      11: iconst_1
      12: anewarray     #396                // class java/nio/file/CopyOption
      15: dup
      16: iconst_0
      17: getstatic     #398                // Field java/nio/file/StandardCopyOption.REPLACE_EXISTING:Ljava/nio/file/StandardCopyOption;
      20: aastore
      21: invokestatic  #404                // Method java/nio/file/Files.copy:(Ljava/nio/file/Path;Ljava/nio/file/Path;[Ljava/nio/file/CopyOption;)Ljava/nio/file/Path;
      24: pop
      25: return

  public java.nio.file.Path mappingsWorkingDir();
    Code:
       0: aload_0
       1: getfield      #13                 // Field mappingsWorkingDir:Ljava/nio/file/Path;
       4: areturn

  public java.lang.String mappingsIdentifier();
    Code:
       0: aload_0
       1: getfield      #7                  // Field mappingsIdentifier:Ljava/lang/String;
       4: areturn

  public java.io.File getUnpickDefinitionsFile();
    Code:
       0: aload_0
       1: getfield      #40                 // Field unpickDefinitions:Ljava/nio/file/Path;
       4: invokeinterface #280,  1          // InterfaceMethod java/nio/file/Path.toFile:()Ljava/io/File;
       9: areturn

  public boolean hasUnpickDefinitions();
    Code:
       0: aload_0
       1: getfield      #227                // Field unpickMetadata:Lnet/fabricmc/loom/configuration/providers/mappings/unpick/UnpickMetadata;
       4: ifnull        11
       7: iconst_1
       8: goto          12
      11: iconst_0
      12: ireturn

  public net.fabricmc.loom.configuration.providers.mappings.unpick.UnpickMetadata getUnpickMetadata();
    Code:
       0: aload_0
       1: getfield      #227                // Field unpickMetadata:Lnet/fabricmc/loom/configuration/providers/mappings/unpick/UnpickMetadata;
       4: ldc_w         #507                // String Unpick metadata is not available
       7: invokestatic  #509                // Method java/util/Objects.requireNonNull:(Ljava/lang/Object;Ljava/lang/String;)Ljava/lang/Object;
      10: checkcast     #232                // class net/fabricmc/loom/configuration/providers/mappings/unpick/UnpickMetadata
      13: areturn

  public java.util.Map<java.lang.String, java.lang.String> getSignatureFixes();
    Code:
       0: aload_0
       1: getfield      #450                // Field signatureFixes:Ljava/util/Map;
       4: areturn

  static {};
    Code:
       0: ldc           #8                  // class net/fabricmc/loom/configuration/providers/mappings/MappingConfiguration
       2: invokestatic  #527                // Method org/slf4j/LoggerFactory.getLogger:(Ljava/lang/Class;)Lorg/slf4j/Logger;
       5: putstatic     #299                // Field LOGGER:Lorg/slf4j/Logger;
       8: return
}
